[
  {
    "isim": "Futbol",
    "logo": "https://raw.githubusercontent.com/Lessonss/apitest/main/futbol.jpg",
    "aciklama": "Futbol oyunu"
  },
   {
    "isim": "Basketbol",
    "logo": "https://raw.githubusercontent.com/Lessonss/apitest/main/basketbol.jpg",
    "aciklama": "Basketbol oyunu"
  }, {
    "isim": "Hentbol",
    "logo": "https://raw.githubusercontent.com/Lessonss/apitest/main/hentbol.jpg",
    "aciklama": "Hentbol oyunu"
  }, {
    "isim": "Voleybol",
    "logo": "https://raw.githubusercontent.com/Lessonss/apitest/main/voleybol.jpg",
    "aciklama": "Voleybol oyunu"
  }, {
    "isim": "Boks",
    "logo": "https://raw.githubusercontent.com/Lessonss/apitest/main/boks.jpg",
    "aciklama": "Boks sporu"
  }
]
